pyecharts_snapshot/__init__.py
pyecharts_snapshot/logger.py
pyecharts_snapshot/main.py
pyecharts_snapshot/phantomjs/snapshot.js
pyecharts_snapshot_pro-0.2.9.dist-info/METADATA
pyecharts_snapshot_pro-0.2.9.dist-info/WHEEL
pyecharts_snapshot_pro-0.2.9.dist-info/entry_points.txt
pyecharts_snapshot_pro-0.2.9.dist-info/top_level.txt
pyecharts_snapshot_pro-0.2.9.dist-info/RECORD
