Metadata-Version: 2.1
Name: pyecharts-snapshot-pro
Version: 0.2.9
Summary: renders pyecharts output as image
Home-page: https://github.com/flytrap/pyecharts-snapshot
Download-URL: https://github.com/flytrap/pyecharts-snapshot/archive/0.2.9.tar.gz
Author: flytrap
Author-email: hiddenstat@gmail.com
License: MIT
Keywords: python,echarts,visualisation,data,utility,png,jpeg,svg,pdf,pyecharts,chart,playwright
Platform: UNKNOWN
Classifier: Topic :: Software Development :: Libraries
Classifier: Programming Language :: Python
Classifier: Intended Audience :: Developers
Classifier: Programming Language :: Python :: 3 :: Only
Classifier: Programming Language :: Python :: 3.5
Classifier: Programming Language :: Python :: 3.6
Classifier: Programming Language :: Python :: 3.7
Classifier: Programming Language :: Python :: 3.8
Requires-Dist: pillow
Requires-Dist: playwright
